Metadata-Version: 2.1
Name: ro-diacritics
Version: 0.9.4.1
Summary: Python API for Romanian diacritics restoration
Home-page: https://github.com/AndyTheFactory/RO-Diacritics
Author: Andrei Paraschiv
Author-email: andrei@thephpfactory.com
Maintainer: Andrei Paraschiv
Maintainer-email: andrei@thephpfactory.com
License: UNKNOWN
Keywords: romanian diacritcs language restoration diacritice python
Platform: UNKNOWN
Classifier: Development Status :: 4 - Beta
Classifier: Intended Audience :: Developers
Classifier: Intended Audience :: Education
Classifier: Intended Audience :: Information Technology
Classifier: Intended Audience :: Science/Research
Classifier: Topic :: Scientific/Engineering
Classifier: Topic :: Scientific/Engineering :: Human Machine Interfaces
Classifier: Topic :: Scientific/Engineering :: Information Analysis
Classifier: Topic :: Text Processing
Classifier: Topic :: Text Processing :: Filters
Classifier: Topic :: Text Processing :: General
Classifier: Topic :: Text Processing :: Indexing
Classifier: Topic :: Text Processing :: Linguistic
Classifier: License :: OSI Approved :: MIT License
Classifier: Programming Language :: Python :: 3
License-File: LICENSE
